itssafe.py
itssafe-1.2.2.dist-info/DESCRIPTION.rst
itssafe-1.2.2.dist-info/METADATA
itssafe-1.2.2.dist-info/RECORD
itssafe-1.2.2.dist-info/WHEEL
itssafe-1.2.2.dist-info/metadata.json
itssafe-1.2.2.dist-info/top_level.txt
