Metadata-Version: 2.0
Name: itssafe
Version: 1.2.2
Summary: A signer and unsigner that can be explained to those who would need to copy the implemenation in non-Python environments
Home-page: https://bitbucket.org/mirusresearch/itssafe
Author: Mirus Research
Author-email: frank@mirusresearch.com
License: MIT license, see LICENSE
Platform: UNKNOWN
Requires-Dist: pytz (>=2017.2)
Requires-Dist: six (>=1.10.0)
